cli_string/__init__.py
cli_string/main.py
cli_string/utils.py
cli_string-0.1.2.dist-info/METADATA
cli_string-0.1.2.dist-info/WHEEL
cli_string-0.1.2.dist-info/entry_points.txt
cli_string-0.1.2.dist-info/RECORD
