Metadata-Version: 2.3
Name: cli_string
Version: 0.1.2
Summary: This CLI tool analyzes a string or a file containing strings and outputs **only the characters that appear exactly once** in each line (case-insensitive). Additionally, it measures the execution time of the function call.
Author: Daniel Kravchenko
Author-email: daniel.kravchenko@protonmail.com
Requires-Python: >=3.12
Classifier: Programming Language :: Python :: 3
Classifier: Programming Language :: Python :: 3.12
Classifier: Programming Language :: Python :: 3.13
Requires-Dist: coverage (>=7.9.2,<8.0.0)
Requires-Dist: pytest (>=8.4.1,<9.0.0)
Requires-Dist: twine (>=6.1.0,<7.0.0)
